yada/__init__.py
yada/argname.py
yada/exceptions.py
yada/ns_parser.py
yada/string_parser.py
yada/yada.py
t2_yada-1.2.2.dist-info/LICENSE
t2_yada-1.2.2.dist-info/METADATA
t2_yada-1.2.2.dist-info/WHEEL
t2_yada-1.2.2.dist-info/RECORD
